cross_nli/__init__.py
cross_nli/cross_nli.py
cross_nli-0.1.0.dist-info/METADATA
cross_nli-0.1.0.dist-info/WHEEL
cross_nli-0.1.0.dist-info/top_level.txt
cross_nli-0.1.0.dist-info/RECORD
