Metadata-Version: 2.2
Name: cross_nli
Version: 0.1.0
Summary: A package for evaluating hallucination and coverage in generated outputs deploying NLI and LLM models
Home-page: https://github.com/gkoumasd/cross_nli
Author: Dimitris Gkoumas
Author-email: gkoumasjim@gmail.com
Classifier: Programming Language :: Python :: 3
Classifier: License :: OSI Approved :: MIT License
Classifier: Operating System :: OS Independent
Requires-Python: >=3.7
Requires-Dist: torch
Requires-Dist: numpy
Requires-Dist: transformers
Requires-Dist: tqdm
Requires-Dist: pandas
Dynamic: author
Dynamic: author-email
Dynamic: classifier
Dynamic: description
Dynamic: description-content-type
Dynamic: home-page
Dynamic: requires-dist
Dynamic: requires-python
Dynamic: summary
